<?xml version="1.0" encoding="UTF-8"?>
<objects serializationModel="Studio.01.07.00">
    <object class="Workspace" id="{5d00ba4e-dd41-4a9e-82f6-f3579339d01d}">
        <property name="outputFormat">
            <value>6</value>
        </property>
        <relationship name="masterEventFolder">
            <destination>{9d7bc9f9-5519-4676-87d8-bb2ef58cee84}</destination>
        </relationship>
        <relationship name="masterTagFolder">
            <destination>{c5c0107e-4d0b-401e-bc91-29f5cbf8bed1}</destination>
        </relationship>
        <relationship name="masterBankFolder">
            <destination>{f78bed8b-7ff6-4795-b67b-81fd5d8b5765}</destination>
        </relationship>
        <relationship name="audioBinManager">
            <destination>{f5748129-e3fe-4c90-96e2-c0bd740fad8a}</destination>
        </relationship>
        <relationship name="mixer">
            <destination>{ddfc9465-f24f-4180-90db-a769d09ee578}</destination>
        </relationship>
    </object>
    <object class="AudioBinManager" id="{f5748129-e3fe-4c90-96e2-c0bd740fad8a}">
        <relationship name="masterAudioBinFolder">
            <destination>{e2201432-bd26-40d3-9e30-75673b0d08f1}</destination>
        </relationship>
    </object>
</objects>
